zipado/Modulos/modulo.v
//Criação do módulo de clock para o sistema
module Clks (
    output reg clk
);
    always @* begin
        #1 //Local para setar o clock (O clk vai ser de x segundos para cada sinal)
        clk <= ~clk; //Após x segundos, o valor do clock vai ser invertido
    end
    initial begin
        clk <= 0; // Inicializa o reg do clk como 0 para ter um valor inicial para o clock
    end
endmodule



//Este será o módulo de codificação das entradas
//Ele vai receber 4 entradas, um sinal de reset e um de ready e vai retornar os valores codificados para cada bit
module mod_Saidas (
    input A, B, C, D, reset, ready,
    output reg S3, S2, S1, S0
);

//Tabelas verdade relacionadas ao grupo 30 (O nosso):
//s3 = CD + A'B'C' + A'BC + AB'C
//s2 = A'C + BC + A'BD' + AB'C'D'
//s1 = A'B'D' + B'C'D' + A'CD + B'CD + BC'D
//s0 = C'D' + A'B'D + ABD

    always @* begin
        // Logica de atribuicao normal
        if (ready) begin
            S3 = ((C&D)|(~A&~B&~C)|(~A&B&C)|(A&~B&C));
            S2 = ((~A&C)|(B&C)|(~A&B&~D)|(A&~B&~C&~D));
            S1 = ((~A&~B&~D)|(~B&~C&~D)|(~A&C&D)|(~B&C&D)|(B&~C&D));
            S0 = ((~C&~D)|(~A&~B&D)|(A&B&D));
        end else begin
            // Logica de atribuicao para estado inicial quando ready nao esta ativo
            S3 = 1'b0;
            S2 = 1'b0;
            S1 = 1'b0;
            S0 = 1'b0;
        end
    end

    // Logica de reset para zerar saidas quando o sinal de reset e acionado
    always @(posedge reset) begin
        if (reset) begin
            S3 <= 1'b0;
            S2 <= 1'b0;
            S1 <= 1'b0;
            S0 <= 1'b0;
            
        end
    end

endmodule




//Modulo responsável pela lógica do Display 
//Recebe o clock do sistema (para atualizar o display), um sinal de reset e de ready
//Uma entrada de um bit e a saída de 7 bits (para o display de 7 segmentos)
module Display(
    input clk, reset, ready,
    input entrada,
    output reg [6:0] display
);

always @(clk or posedge reset) begin // Inicia o laço always para verificar sempre que o clock atualiza ou o reset é ativado
    if (reset) begin
        display = 7'b0000000;        // Se o reset for ativado o display será desligado até o reset ser desligado
    end
    else if (ready) begin            // Caso contrário, quando o ready estiver ativo, ele verifica se a entrada é 0 ou 1
        case (entrada)
            1'b0: display = 7'b0111111; // Se for 0, o display liga os segmentos relacionados ao 0: A, B, C, D, E, F
            1'b1: display = 7'b0000110; // Se for 1, o display liga os segmentos relacionados ao 1: B, C
        endcase
    end
end

endmodule

zipado/Modulos/Testbench.v
`include "modulo.v"

module Testbench ();
    //Define as variáveis para integer, regs e wires que serão utilizados nas funções
    integer i;
    reg [0:3] entrada;
    reg reset, ready;
    wire S3, S2, S1, S0;
    //Define a variável para o clock
    wire clk;
    //Define reset e ready para os displays e também os wires para cada segmento do display para cada numero
    reg resetDisp, readyDisp;
    wire [6:0] displayDisp3;
    wire [6:0] displayDisp2;
    wire [6:0] displayDisp1;
    wire [6:0] displayDisp0;


    //Instancia as funções dando nome para elas e também conectando as entradas e saídas com as regs e wires criadas anteriormente
    Clks clock(.clk(clk));
    mod_Saidas saidas(.A(entrada[0]), .B(entrada[1]), .C(entrada[2]), .D(entrada[3]), .reset(reset), .ready(ready), .S3(S3), .S2(S2), .S1(S1), .S0(S0));
    Display display3(.clk(clk), .reset(resetDisp), .ready(readyDisp), .entrada(S3), .display(displayDisp3));
    Display display2(.clk(clk), .reset(resetDisp), .ready(readyDisp), .entrada(S2), .display(displayDisp2));
    Display display1(.clk(clk), .reset(resetDisp), .ready(readyDisp), .entrada(S1), .display(displayDisp1));
    Display display0(.clk(clk), .reset(resetDisp), .ready(readyDisp), .entrada(S0), .display(displayDisp0));
    
    //TestBench começa aqui
    initial begin
        $dumpfile("teste.vcd"); //Começa a criação do arquivo de ondas
        $dumpvars(0); //Dumpvars com o argumento 0 vai dar registrar todas as variáveis relacionadas ao programa
    
        $display("____________________________");
        $display("| A  B  C  D | S3 S2 S1 S0 |"); //Organiza o display
        $display("|____________|_____________|");
        
        //Inicializa o código dando reset no codificador e no display (para não exibir valores com x ao invés de números legíveis)
        reset = 1;
        reset = 0;
        resetDisp = 1;
        resetDisp = 0;

        ready = 1; // Ready para começar a codificar
        readyDisp = 1; // Ready para começar o display
        entrada = 4'b0000; //Define os valores da entrada anteriormente definidas
        #2;

        // Um laço de for é criado para mostrar e adicionar cada valor da entrada, até adicionar 15 vezes na entrada e ter um vetor 4'b1111
        for (i = 0; i < 16; i = i + 1) begin
            $display("| %0t  %0t  %0t  %0t |  %0t  %0t  %0t  %0t |", entrada[0], entrada[1], entrada[2], entrada[3], S3, S2, S1, S0); // Dá display no terminal a cada vez que o for é percorrido
            #1;
            entrada = entrada + 1;
            #3;
        end
        $display("|____________|_____________|"); //Termina a formatação da tabela verdade no terminal

        //Esta era uma outra forma de adicionar cada valor e dar o display para exibir no terminal
        //Contudo, foi decidido que seria melhor usar o for, já que o mesmo não utiliza tantas linhas
        /*
        //0 -> 11
        A = 0;
        B = 0;
        C = 0; 
        D = 0;
        $display("| A  B  C  D | S1 S2 S3 S4 |");
        $display("| %0t %0t %0t %0t | %0t %0t %0t %0t", A, B, C, D, S3, S2, S1, S0);
        #2;
        //1 -> 9
        A = 0;
        B = 0;
        C = 0;
        D = 1;
        #2;
        //2 -> 6
        A = 0;
        B = 0;
        C = 1;
        D = 0; 
        #2;
        //3 -> 15
        A = 0;
        B = 0;
        C = 1;
        D = 1;
        #2;
        //4 -> 5
        A = 0;
        B = 1;
        C = 0; 
        D = 0;
        #2;
        //5 -> 2
        A = 0;
        B = 1;
        C = 0;
        D = 1;
        #2;
        //6 -> 12
        A = 0;
        B = 1;
        C = 1;
        D = 0; 
        #2;
        //7 -> 14
        A = 0;
        B = 1;
        C = 1;
        D = 1;
        #2;
        //8 -> 7
        A = 1;
        B = 0;
        C = 0; 
        D = 0;
        #2;
        //9 -> 0
        A = 1;
        B = 0;
        C = 0;
        D = 1;
        #2;
        //10 -> 8
        A = 1;
        B = 0;
        C = 1;
        D = 0; 
        #2;
        //11 -> 10
        A = 1;
        B = 0;
        C = 1;
        D = 1;
        #2;
        //12 -> 1
        A = 1;
        B = 1;
        C = 0; 
        D = 0;
        #2;
        //13 -> 3
        A = 1;
        B = 1;
        C = 0;
        D = 1;
        #2;
        //14 -> 4
        A = 1;
        B = 1;
        C = 1;
        D = 0; 
        #2;
        //15 -> 13
        A = 1;
        B = 1;
        C = 1;
        D = 1;
        */
        #10;
        $finish; //Termina o dump das variáveis e cria o arquivo .vcd ao executar o .vvp

    end //Termina o Initial Begin
    
endmodule //Termina o módulo de simulação

zipado/Modulos/teste.vcd
$date
	Sat Oct 07 22:38:10 2023
$end
$version
	Icarus Verilog
$end
$timescale
	1s
$end
$scope module Testbench $end
$var wire 7 ! displayDisp3 [6:0] $end
$var wire 7 " displayDisp2 [6:0] $end
$var wire 7 # displayDisp1 [6:0] $end
$var wire 7 $ displayDisp0 [6:0] $end
$var wire 1 % clk $end
$var wire 1 & S3 $end
$var wire 1 ' S2 $end
$var wire 1 ( S1 $end
$var wire 1 ) S0 $end
$var reg 4 * entrada [0:3] $end
$var reg 1 + ready $end
$var reg 1 , readyDisp $end
$var reg 1 - reset $end
$var reg 1 . resetDisp $end
$var integer 32 / i [31:0] $end
$scope module clock $end
$var reg 1 % clk $end
$upscope $end
$scope module display0 $end
$var wire 1 % clk $end
$var wire 1 , ready $end
$var wire 1 . reset $end
$var wire 1 ) entrada $end
$var reg 7 0 display [6:0] $end
$upscope $end
$scope module display1 $end
$var wire 1 % clk $end
$var wire 1 , ready $end
$var wire 1 . reset $end
$var wire 1 ( entrada $end
$var reg 7 1 display [6:0] $end
$upscope $end
$scope module display2 $end
$var wire 1 % clk $end
$var wire 1 , ready $end
$var wire 1 . reset $end
$var wire 1 ' entrada $end
$var reg 7 2 display [6:0] $end
$upscope $end
$scope module display3 $end
$var wire 1 % clk $end
$var wire 1 , ready $end
$var wire 1 . reset $end
$var wire 1 & entrada $end
$var reg 7 3 display [6:0] $end
$upscope $end
$scope module saidas $end
$var wire 1 4 A $end
$var wire 1 5 B $end
$var wire 1 6 C $end
$var wire 1 7 D $end
$var wire 1 + ready $end
$var wire 1 - reset $end
$var reg 1 ) S0 $end
$var reg 1 ( S1 $end
$var reg 1 ' S2 $end
$var reg 1 & S3 $end
$upscope $end
$upscope $end
$enddefinitions $end
#0
$dumpvars
07
06
05
04
b110 3
b111111 2
b110 1
b110 0
bx /
0.
0-
1,
1+
b0 *
1)
1(
0'
1&
0%
b110 $
b110 #
b111111 "
b110 !
$end
#1
1%
#2
0%
b0 /
#3
b111111 #
b111111 1
1%
0(
17
b1 *
#4
0%
#5
1%
#6
0%
b1 /
#7
b111111 !
b111111 3
b110 "
b110 2
b110 #
b110 1
b111111 $
b111111 0
1%
0)
1(
1'
0&
16
07
b10 *
#8
0%
#9
1%
#10
0%
b10 /
#11
b110 !
b110 3
b110 $
b110 0
1%
1)
1&
17
b11 *
#12
0%
#13
1%
#14
0%
b11 /
#15
b111111 !
b111111 3
b111111 #
b111111 1
1%
0(
0&
15
06
07
b100 *
#16
0%
#17
1%
#18
0%
b100 /
#19
b111111 "
b111111 2
b110 #
b110 1
b111111 $
b111111 0
1%
0)
1(
0'
17
b101 *
#20
0%
#21
1%
#22
0%
b101 /
#23
b110 !
b110 3
b110 "
b110 2
b111111 #
b111111 1
1%
0(
1'
1&
16
07
b110 *
#24
0%
#25
1%
#26
0%
b110 /
#27
b110 #
b110 1
1%
1(
17
b111 *
#28
0%
#29
1%
#30
0%
b111 /
#31
b111111 !
b111111 3
b110 $
b110 0
1%
1)
0&
14
05
06
07
b1000 *
#32
0%
#33
1%
#34
0%
b1000 /
#35
b111111 "
b111111 2
b111111 #
b111111 1
b111111 $
b111111 0
1%
0)
0(
0'
17
b1001 *
#36
0%
#37
1%
#38
0%
b1001 /
#39
b110 !
b110 3
1%
1&
16
07
b1010 *
#40
0%
#41
1%
#42
0%
b1010 /
#43
b110 #
b110 1
1%
1(
17
b1011 *
#44
0%
#45
1%
#46
0%
b1011 /
#47
b111111 !
b111111 3
b111111 #
b111111 1
b110 $
b110 0
1%
1)
0(
0&
15
06
07
b1100 *
#48
0%
#49
1%
#50
0%
b1100 /
#51
b110 #
b110 1
1%
1(
17
b1101 *
#52
0%
#53
1%
#54
0%
b1101 /
#55
b110 "
b110 2
b111111 #
b111111 1
b111111 $
b111111 0
1%
0)
0(
1'
16
07
b1110 *
#56
0%
#57
1%
#58
0%
b1110 /
#59
b110 !
b110 3
b110 $
b110 0
1%
1)
1&
17
b1111 *
#60
0%
#61
1%
#62
0%
b1111 /
#63
b111111 "
b111111 2
b110 #
b110 1
1%
1(
0'
04
05
06
07
b0 *
#64
0%
#65
1%
#66
0%
b10000 /
